{
    "coordinates_type": "EPSG:3857",
    "region": [
        -44646.36822336761,
        4776255.401946893,
        -44389.897438641376,
        4776511.872731619
    ],
    "resolution": [
        1280,
        1280
    ],
    "meters_per_pixel": 0.20036780056737133,
    "lanes": [
        {
            "road_id": "00010300",
            "lane_id": "00000100",
            "single": true,
            "white": true,
            "solid": false,
            "vertices": [
                [
                    863,
                    -72
                ],
                [
                    781,
                    91
                ],
                [
                    698,
                    271
                ],
                [
                    692,
                    286
                ]
            ]
        },
        {
            "road_id": "00010300",
            "lane_id": "00000200",
            "single": true,
            "white": true,
            "solid": false,
            "vertices": [
                [
                    963,
                    -212
                ],
                [
                    849,
                    6
                ],
                [
                    762,
                    187
                ],
                [
                    715,
                    294
                ]
            ]
        },
        {
            "road_id": "00010300",
            "lane_id": "00000300",
            "single": true,
            "white": true,
            "solid": true,
            "vertices": [
                [
                    952,
                    -145
                ],
                [
                    874,
                    13
                ],
                [
                    815,
                    131
                ],
                [
                    778,
                    210
                ],
                [
                    738,
                    301
                ]
            ]
        },
        {
            "road_id": "00010400",
            "lane_id": "00000000",
            "single": true,
            "white": true,
            "solid": true,
            "vertices": [
                [
                    1055,
                    -275
                ],
                [
                    878,
                    69
                ],
                [
                    795,
                    247
                ],
                [
                    720,
                    424
                ],
                [
                    645,
                    626
                ],
                [
                    641,
                    636
                ]
            ]
        },
        {
            "road_id": "00010400",
            "lane_id": "00000100",
            "single": true,
            "white": true,
            "solid": false,
            "vertices": [
                [
                    1016,
                    -151
                ],
                [
                    902,
                    72
                ],
                [
                    815,
                    256
                ],
                [
                    748,
                    421
                ],
                [
                    673,
                    614
                ],
                [
                    663,
                    643
                ]
            ]
        },
        {
            "road_id": "00010400",
            "lane_id": "00003000",
            "single": true,
            "white": true,
            "solid": true,
            "vertices": [
                [
                    1023,
                    -116
                ],
                [
                    956,
                    23
                ],
                [
                    893,
                    145
                ],
                [
                    828,
                    285
                ],
                [
                    786,
                    383
                ],
                [
                    717,
                    563
                ],
                [
                    684,
                    651
                ]
            ]
        },
        {
            "road_id": "00010500",
            "lane_id": "00000100",
            "single": true,
            "white": true,
            "solid": false,
            "vertices": [
                [
                    691,
                    287
                ],
                [
                    617,
                    477
                ],
                [
                    544,
                    678
                ],
                [
                    472,
                    875
                ],
                [
                    396,
                    1077
                ],
                [
                    314,
                    1268
                ],
                [
                    235,
                    1428
                ]
            ]
        },
        {
            "road_id": "00010500",
            "lane_id": "00000200",
            "single": true,
            "white": true,
            "solid": false,
            "vertices": [
                [
                    714,
                    296
                ],
                [
                    687,
                    359
                ],
                [
                    638,
                    484
                ],
                [
                    577,
                    655
                ],
                [
                    533,
                    776
                ],
                [
                    482,
                    913
                ],
                [
                    434,
                    1042
                ],
                [
                    379,
                    1180
                ],
                [
                    329,
                    1291
                ],
                [
                    288,
                    1374
                ]
            ]
        },
        {
            "road_id": "00010500",
            "lane_id": "00000300",
            "single": true,
            "white": true,
            "solid": true,
            "vertices": [
                [
                    737,
                    304
                ],
                [
                    736,
                    306
                ],
                [
                    703,
                    387
                ],
                [
                    673,
                    462
                ],
                [
                    595,
                    671
                ],
                [
                    535,
                    840
                ],
                [
                    495,
                    948
                ],
                [
                    460,
                    1042
                ],
                [
                    408,
                    1167
                ],
                [
                    376,
                    1246
                ],
                [
                    343,
                    1317
                ],
                [
                    305,
                    1390
                ]
            ]
        },
        {
            "road_id": "00004300",
            "lane_id": "00000000",
            "single": true,
            "white": true,
            "solid": true,
            "vertices": [
                [
                    658,
                    279
                ],
                [
                    625,
                    351
                ],
                [
                    594,
                    420
                ],
                [
                    561,
                    497
                ],
                [
                    534,
                    567
                ],
                [
                    508,
                    638
                ],
                [
                    487,
                    695
                ],
                [
                    458,
                    775
                ],
                [
                    419,
                    884
                ],
                [
                    370,
                    1016
                ],
                [
                    329,
                    1112
                ],
                [
                    293,
                    1196
                ],
                [
                    259,
                    1273
                ],
                [
                    224,
                    1346
                ]
            ]
        },
        {
            "road_id": "00004400",
            "lane_id": "00000000",
            "single": true,
            "white": true,
            "solid": true,
            "vertices": [
                [
                    716,
                    662
                ],
                [
                    685,
                    748
                ],
                [
                    668,
                    807
                ],
                [
                    638,
                    887
                ],
                [
                    617,
                    950
                ],
                [
                    591,
                    1028
                ],
                [
                    552,
                    1132
                ],
                [
                    530,
                    1196
                ],
                [
                    481,
                    1306
                ],
                [
                    445,
                    1380
                ]
            ]
        },
        {
            "road_id": "00010300",
            "lane_id": "00002200",
            "single": true,
            "white": true,
            "solid": true,
            "vertices": [
                [
                    870,
                    -139
                ],
                [
                    778,
                    41
                ],
                [
                    715,
                    168
                ],
                [
                    698,
                    202
                ],
                [
                    662,
                    273
                ]
            ]
        },
        {
            "road_id": "00010500",
            "lane_id": "00002400",
            "single": true,
            "white": true,
            "solid": false,
            "vertices": [
                [
                    670,
                    281
                ],
                [
                    601,
                    450
                ],
                [
                    578,
                    516
                ],
                [
                    545,
                    604
                ],
                [
                    481,
                    776
                ],
                [
                    437,
                    905
                ],
                [
                    380,
                    1051
                ],
                [
                    340,
                    1150
                ]
            ]
        },
        {
            "road_id": "00010500",
            "lane_id": "00002500",
            "single": true,
            "white": true,
            "solid": true,
            "vertices": [
                [
                    340,
                    1151
                ],
                [
                    312,
                    1217
                ],
                [
                    276,
                    1295
                ],
                [
                    240,
                    1367
                ]
            ]
        },
        {
            "road_id": "00010400",
            "lane_id": "00002500",
            "single": true,
            "white": true,
            "solid": true,
            "vertices": [
                [
                    1028,
                    -75
                ],
                [
                    970,
                    41
                ],
                [
                    919,
                    143
                ],
                [
                    864,
                    261
                ],
                [
                    820,
                    364
                ],
                [
                    790,
                    445
                ],
                [
                    745,
                    576
                ],
                [
                    717,
                    656
                ]
            ]
        },
        {
            "road_id": "00010600",
            "lane_id": "00002600",
            "single": true,
            "white": true,
            "solid": false,
            "vertices": [
                [
                    706,
                    657
                ],
                [
                    640,
                    841
                ],
                [
                    555,
                    1070
                ],
                [
                    531,
                    1127
                ],
                [
                    511,
                    1180
                ]
            ]
        },
        {
            "road_id": "00010600",
            "lane_id": "00002700",
            "single": true,
            "white": true,
            "solid": true,
            "vertices": [
                [
                    511,
                    1182
                ],
                [
                    448,
                    1326
                ],
                [
                    405,
                    1416
                ]
            ]
        },
        {
            "road_id": "00010600",
            "lane_id": "00000000",
            "single": true,
            "white": true,
            "solid": true,
            "vertices": [
                [
                    640,
                    640
                ],
                [
                    517,
                    976
                ],
                [
                    422,
                    1218
                ],
                [
                    367,
                    1340
                ],
                [
                    300,
                    1473
                ]
            ]
        },
        {
            "road_id": "00010600",
            "lane_id": "00000100",
            "single": true,
            "white": true,
            "solid": false,
            "vertices": [
                [
                    662,
                    644
                ],
                [
                    591,
                    844
                ],
                [
                    514,
                    1048
                ],
                [
                    431,
                    1254
                ],
                [
                    375,
                    1374
                ]
            ]
        },
        {
            "road_id": "00010600",
            "lane_id": "00000200",
            "single": true,
            "white": true,
            "solid": true,
            "vertices": [
                [
                    683,
                    652
                ],
                [
                    645,
                    753
                ],
                [
                    589,
                    920
                ],
                [
                    550,
                    1016
                ],
                [
                    477,
                    1199
                ],
                [
                    425,
                    1323
                ],
                [
                    368,
                    1437
                ]
            ]
        }
    ]
}