{
    "coordinates_type": "EPSG:3857",
    "region": [
        3510001.4701213883,
        3494394.5652054795,
        3510357.008040293,
        3494750.1031243843
    ],
    "resolution": [
        1280,
        1280
    ],
    "meters_per_pixel": 0.27776399914403255,
    "lanes": [
        {
            "road_id": "10000000",
            "lane_id": "00000000",
            "single": true,
            "white": true,
            "solid": true,
            "vertices": [
                [
                    -100,
                    886
                ],
                [
                    -7,
                    873
                ],
                [
                    60,
                    865
                ],
                [
                    156,
                    858
                ],
                [
                    243,
                    858
                ],
                [
                    327,
                    859
                ],
                [
                    425,
                    865
                ],
                [
                    524,
                    879
                ],
                [
                    621,
                    896
                ],
                [
                    726,
                    917
                ],
                [
                    775,
                    930
                ],
                [
                    873,
                    960
                ]
            ]
        },
        {
            "road_id": "10000000",
            "lane_id": "00000100",
            "single": true,
            "white": true,
            "solid": true,
            "vertices": [
                [
                    -70,
                    870
                ],
                [
                    -13,
                    861
                ],
                [
                    38,
                    855
                ],
                [
                    90,
                    850
                ],
                [
                    170,
                    846
                ],
                [
                    227,
                    846
                ],
                [
                    302,
                    847
                ],
                [
                    375,
                    850
                ],
                [
                    417,
                    853
                ],
                [
                    473,
                    859
                ],
                [
                    527,
                    866
                ],
                [
                    609,
                    881
                ],
                [
                    667,
                    892
                ],
                [
                    744,
                    909
                ],
                [
                    792,
                    923
                ],
                [
                    877,
                    949
                ]
            ]
        },
        {
            "road_id": "10000000",
            "lane_id": "00000200",
            "single": true,
            "white": true,
            "solid": true,
            "vertices": [
                [
                    -70,
                    855
                ],
                [
                    0,
                    846
                ],
                [
                    57,
                    840
                ],
                [
                    140,
                    834
                ],
                [
                    193,
                    833
                ],
                [
                    267,
                    834
                ],
                [
                    319,
                    834
                ],
                [
                    395,
                    838
                ],
                [
                    450,
                    843
                ],
                [
                    505,
                    849
                ],
                [
                    561,
                    858
                ],
                [
                    647,
                    875
                ],
                [
                    711,
                    889
                ],
                [
                    785,
                    906
                ],
                [
                    879,
                    936
                ]
            ]
        },
        {
            "road_id": "10000000",
            "lane_id": "00000300",
            "single": true,
            "white": true,
            "solid": true,
            "vertices": [
                [
                    -92,
                    847
                ],
                [
                    -38,
                    839
                ],
                [
                    10,
                    833
                ],
                [
                    91,
                    825
                ],
                [
                    177,
                    820
                ],
                [
                    224,
                    820
                ],
                [
                    316,
                    822
                ],
                [
                    394,
                    826
                ],
                [
                    457,
                    831
                ],
                [
                    542,
                    844
                ],
                [
                    621,
                    858
                ],
                [
                    705,
                    875
                ],
                [
                    787,
                    895
                ],
                [
                    883,
                    924
                ]
            ]
        },
        {
            "road_id": "10000000",
            "lane_id": "00000400",
            "single": true,
            "white": true,
            "solid": true,
            "vertices": [
                [
                    -91,
                    833
                ],
                [
                    -25,
                    823
                ],
                [
                    97,
                    811
                ],
                [
                    204,
                    808
                ],
                [
                    310,
                    808
                ],
                [
                    391,
                    812
                ],
                [
                    511,
                    825
                ],
                [
                    591,
                    838
                ],
                [
                    690,
                    858
                ],
                [
                    762,
                    875
                ],
                [
                    888,
                    912
                ]
            ]
        },
        {
            "road_id": "10000000",
            "lane_id": "00000500",
            "single": true,
            "white": true,
            "solid": false,
            "vertices": [
                [
                    873,
                    960
                ],
                [
                    916,
                    974
                ],
                [
                    966,
                    991
                ],
                [
                    1070,
                    1024
                ],
                [
                    1179,
                    1061
                ],
                [
                    1282,
                    1093
                ],
                [
                    1389,
                    1128
                ]
            ]
        },
        {
            "road_id": "10000000",
            "lane_id": "00000600",
            "single": true,
            "white": true,
            "solid": false,
            "vertices": [
                [
                    878,
                    949
                ],
                [
                    973,
                    979
                ],
                [
                    1076,
                    1013
                ],
                [
                    1181,
                    1048
                ],
                [
                    1287,
                    1082
                ],
                [
                    1395,
                    1116
                ]
            ]
        },
        {
            "road_id": "10000000",
            "lane_id": "00000700",
            "single": true,
            "white": true,
            "solid": false,
            "vertices": [
                [
                    880,
                    936
                ],
                [
                    969,
                    966
                ],
                [
                    1078,
                    1000
                ],
                [
                    1185,
                    1035
                ],
                [
                    1289,
                    1069
                ],
                [
                    1395,
                    1103
                ]
            ]
        },
        {
            "road_id": "10000000",
            "lane_id": "00000800",
            "single": true,
            "white": true,
            "solid": false,
            "vertices": [
                [
                    884,
                    925
                ],
                [
                    979,
                    956
                ],
                [
                    1082,
                    989
                ],
                [
                    1187,
                    1023
                ],
                [
                    1293,
                    1057
                ],
                [
                    1403,
                    1093
                ]
            ]
        },
        {
            "road_id": "10000000",
            "lane_id": "00000900",
            "single": true,
            "white": true,
            "solid": false,
            "vertices": [
                [
                    889,
                    913
                ],
                [
                    983,
                    944
                ],
                [
                    1087,
                    977
                ],
                [
                    1192,
                    1012
                ],
                [
                    1301,
                    1046
                ],
                [
                    1406,
                    1081
                ]
            ]
        },
        {
            "road_id": "10000000",
            "lane_id": "00002000",
            "single": true,
            "white": true,
            "solid": true,
            "vertices": [
                [
                    -119,
                    825
                ],
                [
                    -50,
                    814
                ],
                [
                    4,
                    808
                ],
                [
                    74,
                    802
                ],
                [
                    132,
                    797
                ],
                [
                    220,
                    794
                ],
                [
                    278,
                    795
                ],
                [
                    356,
                    798
                ],
                [
                    416,
                    802
                ],
                [
                    489,
                    810
                ],
                [
                    552,
                    819
                ],
                [
                    635,
                    834
                ],
                [
                    691,
                    845
                ],
                [
                    748,
                    859
                ],
                [
                    817,
                    878
                ],
                [
                    888,
                    899
                ],
                [
                    984,
                    931
                ],
                [
                    1038,
                    948
                ],
                [
                    1109,
                    971
                ],
                [
                    1174,
                    992
                ],
                [
                    1257,
                    1019
                ],
                [
                    1319,
                    1039
                ],
                [
                    1403,
                    1066
                ]
            ]
        },
        {
            "road_id": "10000000",
            "lane_id": "00002100",
            "single": true,
            "white": true,
            "solid": true,
            "vertices": [
                [
                    -79,
                    894
                ],
                [
                    -9,
                    886
                ],
                [
                    75,
                    876
                ],
                [
                    157,
                    871
                ],
                [
                    220,
                    870
                ],
                [
                    294,
                    871
                ],
                [
                    353,
                    874
                ],
                [
                    433,
                    880
                ],
                [
                    538,
                    892
                ],
                [
                    602,
                    904
                ],
                [
                    680,
                    921
                ],
                [
                    738,
                    934
                ],
                [
                    790,
                    948
                ],
                [
                    859,
                    970
                ],
                [
                    915,
                    988
                ],
                [
                    1006,
                    1016
                ],
                [
                    1099,
                    1046
                ],
                [
                    1197,
                    1079
                ],
                [
                    1281,
                    1106
                ],
                [
                    1381,
                    1139
                ]
            ]
        },
        {
            "road_id": "10000100",
            "lane_id": "00000000",
            "single": true,
            "white": true,
            "solid": true,
            "vertices": [
                [
                    -72,
                    618
                ],
                [
                    24,
                    601
                ],
                [
                    140,
                    590
                ],
                [
                    210,
                    589
                ],
                [
                    278,
                    591
                ],
                [
                    338,
                    596
                ],
                [
                    400,
                    606
                ],
                [
                    459,
                    616
                ],
                [
                    552,
                    639
                ],
                [
                    628,
                    662
                ]
            ]
        },
        {
            "road_id": "10000100",
            "lane_id": "00000100",
            "single": true,
            "white": true,
            "solid": true,
            "vertices": [
                [
                    -113,
                    616
                ],
                [
                    -29,
                    599
                ],
                [
                    76,
                    584
                ],
                [
                    171,
                    576
                ],
                [
                    258,
                    576
                ],
                [
                    346,
                    586
                ],
                [
                    477,
                    608
                ],
                [
                    562,
                    628
                ],
                [
                    633,
                    650
                ]
            ]
        },
        {
            "road_id": "10000100",
            "lane_id": "00000200",
            "single": true,
            "white": true,
            "solid": true,
            "vertices": [
                [
                    -136,
                    610
                ],
                [
                    -61,
                    593
                ],
                [
                    20,
                    577
                ],
                [
                    129,
                    566
                ],
                [
                    217,
                    564
                ],
                [
                    289,
                    567
                ],
                [
                    366,
                    575
                ],
                [
                    484,
                    596
                ],
                [
                    547,
                    611
                ],
                [
                    638,
                    639
                ]
            ]
        },
        {
            "road_id": "10000100",
            "lane_id": "00000300",
            "single": true,
            "white": true,
            "solid": true,
            "vertices": [
                [
                    -65,
                    580
                ],
                [
                    11,
                    565
                ],
                [
                    91,
                    555
                ],
                [
                    163,
                    553
                ],
                [
                    237,
                    552
                ],
                [
                    317,
                    556
                ],
                [
                    385,
                    566
                ],
                [
                    471,
                    582
                ],
                [
                    558,
                    602
                ],
                [
                    641,
                    626
                ]
            ]
        },
        {
            "road_id": "10000100",
            "lane_id": "00000400",
            "single": true,
            "white": true,
            "solid": true,
            "vertices": [
                [
                    -93,
                    572
                ],
                [
                    2,
                    554
                ],
                [
                    99,
                    543
                ],
                [
                    187,
                    538
                ],
                [
                    271,
                    541
                ],
                [
                    372,
                    550
                ],
                [
                    452,
                    564
                ],
                [
                    546,
                    584
                ],
                [
                    612,
                    605
                ],
                [
                    646,
                    615
                ]
            ]
        },
        {
            "road_id": "10000100",
            "lane_id": "00000500",
            "single": true,
            "white": true,
            "solid": true,
            "vertices": [
                [
                    -123,
                    566
                ],
                [
                    -57,
                    551
                ],
                [
                    42,
                    537
                ],
                [
                    145,
                    527
                ],
                [
                    237,
                    529
                ],
                [
                    311,
                    531
                ],
                [
                    414,
                    543
                ],
                [
                    493,
                    559
                ],
                [
                    567,
                    578
                ],
                [
                    665,
                    608
                ],
                [
                    819,
                    659
                ],
                [
                    919,
                    691
                ],
                [
                    1123,
                    757
                ],
                [
                    1225,
                    790
                ],
                [
                    1322,
                    822
                ],
                [
                    1425,
                    854
                ]
            ]
        },
        {
            "road_id": "10000100",
            "lane_id": "00000600",
            "single": true,
            "white": true,
            "solid": true,
            "vertices": [
                [
                    -71,
                    632
                ],
                [
                    9,
                    616
                ],
                [
                    87,
                    607
                ],
                [
                    185,
                    601
                ],
                [
                    277,
                    603
                ],
                [
                    371,
                    613
                ],
                [
                    436,
                    624
                ],
                [
                    528,
                    644
                ],
                [
                    721,
                    706
                ],
                [
                    901,
                    764
                ],
                [
                    1030,
                    805
                ],
                [
                    1225,
                    868
                ],
                [
                    1350,
                    908
                ]
            ]
        },
        {
            "road_id": "10000100",
            "lane_id": "00000700",
            "single": true,
            "white": true,
            "solid": false,
            "vertices": [
                [
                    630,
                    662
                ],
                [
                    743,
                    700
                ],
                [
                    847,
                    734
                ],
                [
                    950,
                    767
                ],
                [
                    1052,
                    800
                ],
                [
                    1156,
                    834
                ],
                [
                    1258,
                    867
                ],
                [
                    1365,
                    902
                ]
            ]
        },
        {
            "road_id": "10000100",
            "lane_id": "00000800",
            "single": true,
            "white": true,
            "solid": false,
            "vertices": [
                [
                    635,
                    651
                ],
                [
                    747,
                    688
                ],
                [
                    851,
                    721
                ],
                [
                    956,
                    756
                ],
                [
                    1055,
                    788
                ],
                [
                    1159,
                    821
                ],
                [
                    1265,
                    855
                ],
                [
                    1368,
                    889
                ]
            ]
        },
        {
            "road_id": "10000100",
            "lane_id": "00000900",
            "single": true,
            "white": true,
            "solid": false,
            "vertices": [
                [
                    640,
                    640
                ],
                [
                    752,
                    677
                ],
                [
                    858,
                    711
                ],
                [
                    957,
                    743
                ],
                [
                    1062,
                    778
                ],
                [
                    1166,
                    810
                ],
                [
                    1268,
                    843
                ],
                [
                    1375,
                    879
                ]
            ]
        },
        {
            "road_id": "10000100",
            "lane_id": "00001000",
            "single": true,
            "white": true,
            "solid": false,
            "vertices": [
                [
                    643,
                    628
                ],
                [
                    758,
                    665
                ],
                [
                    860,
                    699
                ],
                [
                    961,
                    731
                ],
                [
                    1068,
                    766
                ],
                [
                    1168,
                    798
                ],
                [
                    1276,
                    834
                ],
                [
                    1379,
                    866
                ]
            ]
        },
        {
            "road_id": "10000100",
            "lane_id": "00001100",
            "single": true,
            "white": true,
            "solid": false,
            "vertices": [
                [
                    648,
                    616
                ],
                [
                    761,
                    653
                ],
                [
                    863,
                    686
                ],
                [
                    962,
                    718
                ],
                [
                    1072,
                    753
                ],
                [
                    1174,
                    787
                ],
                [
                    1282,
                    821
                ],
                [
                    1384,
                    855
                ]
            ]
        }
    ]
}